custos/__init__.py
custos/clients/__init__.py
custos/clients/agent_management_client.py
custos/clients/group_management_client.py
custos/clients/identity_management_client.py
custos/clients/resource_secret_management_client.py
custos/clients/sharing_management_client.py
custos/clients/super_tenant_management_client.py
custos/clients/tenant_management_client.py
custos/clients/user_management_client.py
custos/clients/utils/__init__.py
custos/clients/utils/certificate_fetching_rest_client.py
custos/clients/utils/utilities.py
custos/clients/utils/exceptions/CustosExceptions.py
custos/clients/utils/exceptions/__init__.py
custos/samples/__init__.py
custos/samples/agent_management_samples.py
custos/samples/group_management_samples.py
custos/samples/identity_management_samples.py
custos/samples/resource_secert_management.py
custos/samples/tenant_management_samples.py
custos/samples/user_management_samples.py
custos/samples/resources/__init__.py
custos/samples/resources/cert.pem
custos/server/__init__.py
custos/server/core/AgentProfileService_pb2.py
custos/server/core/AgentProfileService_pb2_grpc.py
custos/server/core/ClusterManagementService_pb2.py
custos/server/core/ClusterManagementService_pb2_grpc.py
custos/server/core/CredentialStoreService_pb2.py
custos/server/core/CredentialStoreService_pb2_grpc.py
custos/server/core/FederatedAuthenticationService_pb2.py
custos/server/core/FederatedAuthenticationService_pb2_grpc.py
custos/server/core/IamAdminService_pb2.py
custos/server/core/IamAdminService_pb2_grpc.py
custos/server/core/IdentityService_pb2.py
custos/server/core/IdentityService_pb2_grpc.py
custos/server/core/LoggingService_pb2.py
custos/server/core/LoggingService_pb2_grpc.py
custos/server/core/MessagingService_pb2.py
custos/server/core/MessagingService_pb2_grpc.py
custos/server/core/ResourceSecretService_pb2.py
custos/server/core/ResourceSecretService_pb2_grpc.py
custos/server/core/SharingService_pb2.py
custos/server/core/SharingService_pb2_grpc.py
custos_sdk-1.0.18.dist-info/LICENSE
custos_sdk-1.0.18.dist-info/METADATA
custos_sdk-1.0.18.dist-info/WHEEL
custos_sdk-1.0.18.dist-info/top_level.txt
custos_sdk-1.0.18.dist-info/RECORD
